lumiwealth_tradier/__init__.py
lumiwealth_tradier/account.py
lumiwealth_tradier/base.py
lumiwealth_tradier/market.py
lumiwealth_tradier/orders.py
lumiwealth_tradier/tradier.py
lumiwealth_tradier-0.1.18.dist-info/licenses/LICENSE
tests/__init__.py
tests/test_account.py
tests/test_market.py
tests/test_orders.py
tests/test_requests_retry_session_thread_safety.py
tests/test_tradier_api_base.py
lumiwealth_tradier-0.1.18.dist-info/METADATA
lumiwealth_tradier-0.1.18.dist-info/WHEEL
lumiwealth_tradier-0.1.18.dist-info/top_level.txt
lumiwealth_tradier-0.1.18.dist-info/RECORD
