Metadata-Version: 2.4
Name: lumiwealth-tradier
Version: 0.1.18
Summary: lumiwealth-tradier is a Python package that serves as a wrapper for the Tradier brokerage API. This package simplifies the process of making API requests, handling responses, and performing various trading and account management operations.
Home-page: https://github.com/Lumiwealth/lumiwealth-tradier
Author: David MacLeod and Robert Grzesik
Project-URL: Bug Tracker, https://github.com/Lumiwealth/lumiwealth-tradier/issues
Keywords: tradier finance api
Requires-Python: >=3.9
License-File: LICENSE
Requires-Dist: pandas>=2.0.0
Requires-Dist: numpy
Dynamic: author
Dynamic: description
Dynamic: description-content-type
Dynamic: home-page
Dynamic: keywords
Dynamic: license-file
Dynamic: project-url
Dynamic: requires-dist
Dynamic: requires-python
Dynamic: summary
